{
  "query": "Dragon Fruit nutritional value",
  "timestamp": "",
  "results": [
    {
      "title": "Dragon fruit | A one piece game Wiki | Fandom",
      "url": "https://bossstudio.fandom.com/wiki/Dragon_fruit",
      "description": "6 Mythical Zoan The Dragon Fruit, also known as Uo Uo no Mi, is one of the Rarity Devil Fruits The fruit is spherical and slightly oblong in shape, somewhat resembling a pinecone. Its blue exterior gives the appearance of having overlapping scales: each &quot;scale&quot; has a small, dark-blue oval in ...",
      "published": "",
      "thumbnail": "https://imgs.search.brave.com/jrnr2RJpkuIlW4YctOzaPr_Ch5wmu_V9cfnh0XCkQNA/rs:fit:200:200:1:0/g:ce/aHR0cHM6Ly9zdGF0/aWMud2lraWEubm9j/b29raWUubmV0L2Jv/c3NzdHVkaW8vaW1h/Z2VzLzgvODYvT2Jy/YXpfMjAyMi0wOC0z/MV8xMzA5MzYwMjAu/d2VicC9yZXZpc2lv/bi9sYXRlc3Q_Y2I9/MjAyMjExMDExNTQy/MTA"
    }
  ]
}